ajnlppreproc/__init__.py
ajnlppreproc/utils.py
ajnlppreproc-0.2.dist-info/LICENSE.txt
ajnlppreproc-0.2.dist-info/METADATA
ajnlppreproc-0.2.dist-info/WHEEL
ajnlppreproc-0.2.dist-info/top_level.txt
ajnlppreproc-0.2.dist-info/RECORD
