Metadata-Version: 2.1
Name: ajnlppreproc
Version: 0.2
Summary: This is a natural language processing library for cleaning and preprocessing of the data
Home-page: UNKNOWN
Author: akhil janardhan
Author-email: akhilchatgpt@gmail.com
License: UNKNOWN
Platform: UNKNOWN
Classifier: Programming Language :: Python :: 3
Classifier: License :: OSI Approved :: MIT License
Classifier: Operating System :: OS Independent
License-File: LICENSE.txt
